![[Pasted image 20260518121056.png|490]]


Here's a **step-by-step walkthrough** of how Java architecture works internally, from writing code to execution on the CPU.

---

## The Complete Java Execution Process

```
┌─────────────┐     ┌──────────────┐     ┌─────────────┐     ┌──────────────┐
│  .java file │ ──→ │  Compiler    │ ──→ │  Bytecode   │ ──→ │    JVM       │
│  (Source)   │     │  (javac)     │     │  (.class)   │     │ (Interpreter │
└─────────────┘     └──────────────┘     └─────────────┘     │  + JIT)      │
                                                             └──────┬───────┘
                                                                    ↓
                                                             ┌──────────────┐
                                                             │ Machine Code │
                                                             │   (CPU)      │
                                                             └──────────────┘
```

---

## Phase 1: Writing Source Code

You write a `.java` file:

```java
// Hello.java
public class Hello {
    public static void main(String[] args) {
        int a = 10;
        int b = 20;
        int sum = a + b;
        System.out.println("Sum: " + sum);
    }
}
```

---

## Phase 2: Compilation (javac)

The **compiler** (`javac`) converts human-readable code into **bytecode**:

### What the compiler does:
1. **Lexical Analysis** – Breaks code into tokens (keywords, identifiers, operators)
2. **Syntax Parsing** – Checks grammar against Java language spec
3. **Semantic Analysis** – Type checking, variable initialization, method existence
4. **Bytecode Generation** – Produces `.class` file with magic numbers, constant pool, method bytecode

### Resulting bytecode (partial view):
```
Compiled from "Hello.java"
public class Hello {
  public Hello();
    Code:
       0: aload_0
       1: invokespecial #1  // Method java/lang/Object."<init>":()V
       4: return

  public static void main(java.lang.String[]);
    Code:
       0: bipush        10
       2: istore_1
       3: bipush        20
       5: istore_2
       6: iload_1
       7: iload_2
       8: iadd
       9: istore_3
      10: getstatic     #2  // Field java/lang/System.out:Ljava/io/PrintStream;
      13: iload_3
      14: invokedynamic #3  // makeConcatWithConstants:(I)Ljava/lang/String;
      19: invokevirtual #4  // Method java/io/PrintStream.println:(Ljava/lang/String;)V
      22: return
}
```

> **Key insight**: Bytecode is **NOT** machine code. It's an intermediate representation that JVM understands.

---
## [[JVM Phase 3 Class Loading (into JVM) 4 Class Loading (into JVM) and 5 Bytecode Execution (Execution Engine)]]

---

## Phase 6: Complete Execution Trace (Concrete Example)

Let's trace `int sum = a + b;` from source to CPU:

```
SOURCE CODE
───────────
int a = 10;
int b = 20;
int sum = a + b;

        ↓ (javac compilation)

BYTECODE
────────
0: bipush 10      // Push 10 onto operand stack
2: istore_1       // Store 10 into local var #1 (a)
3: bipush 20      // Push 20 onto stack
5: istore_2       // Store into local var #2 (b)
6: iload_1        // Push a's value onto stack
7: iload_2        // Push b's value onto stack
8: iadd           // Pop both, add them, push result
9: istore_3       // Store result into local var #3 (sum)

        ↓ (JVM execution)

JVM ACTION (for iadd)
─────────────────────
Stack before: [10, 20]
1. Pop top two values (20, 10)
2. CPU executes ADD instruction
3. Push result (30) back to stack

        ↓ (JIT may optimize)

MACHINE CODE (x86 example)
──────────────────────────
mov eax, [ebp-4]    ; load a into register
add eax, [ebp-8]    ; add b to register
mov [ebp-12], eax   ; store result to sum
```

---

## The Complete Architecture Diagram

```
┌────────────────────────────────────────────────────────────────────┐
│                           JAVA APPLICATION                         │
│                            (.java files)                           │
└─────────────────────────────────┬──────────────────────────────────┘
                                  │ javac
                                  ↓
┌────────────────────────────────────────────────────────────────────┐
│                         BYTECODE (.class)                          │
│                    "Write Once, Run Anywhere"                      │
└─────────────────────────────────┬──────────────────────────────────┘
                                  │ java command
                                  ↓
┌────────────────────────────────────────────────────────────────────┐
│                          JVM (per platform)                        │
├────────────────────────────────────────────────────────────────────┤
│  ┌──────────────┐    ┌──────────────┐    ┌──────────────┐         │
│  │Class Loader  │───→│Memory Areas  │←───│Garbage       │         │
│  │(Loads .class)│    │(Stack, Heap) │    │Collector     │         │
│  └──────────────┘    └──────────────┘    └──────────────┘         │
│         ↓                   ↓                                       │
│  ┌──────────────────────────────────────────┐                     │
│  │         Execution Engine                  │                     │
│  ├─────────────────┬────────────────────────┤                     │
│  │   Interpreter   │   JIT Compiler         │                     │
│  │ (runs bytecode) │ (optimizes hot spots)  │                     │
│  └─────────────────┴────────────────────────┘                     │
└─────────────────────────────────┬──────────────────────────────────┘
                                  │ Native calls
                                  ↓
┌────────────────────────────────────────────────────────────────────┐
│                        OPERATING SYSTEM                            │
│                    (Windows/Linux/macOS)                           │
└─────────────────────────────────┬──────────────────────────────────┘
                                  │
                                  ↓
┌────────────────────────────────────────────────────────────────────┐
│                            HARDWARE                                 │
│                             (CPU/RAM)                               │
└────────────────────────────────────────────────────────────────────┘
```

---

## Key Takeaways for Advanced Java

| Concept | Why it matters in Advanced Java |
|---------|--------------------------------|
| **JIT Compilation** | Optimize performance: use `-XX:+PrintCompilation` to see JIT in action |
| **Class Loaders** | Custom classloaders for hot deployment, plugin architectures |
| **Garbage Collection** | Tuning GC (G1, ZGC) for low-latency apps |
| **Stack vs Heap** | Memory leaks happen in heap; stack overflows from recursion |
| **Bytecode** | Bytecode manipulation (ASM, ByteBuddy) for frameworks like Spring/Hibernate |

---

## Quick Simulation: Run This Mentally

```java
public class Test {
    int x = 5;
    static int y = 10;
    
    public static void main(String[] args) {
        Test obj = new Test();
        int z = obj.x + y;
    }
}
```

**Execution order:**
1. `java Test` → Class loader loads `Test.class`
2. Method area gets static `y = 10`
3. `main` invoked → new stack frame
4. `new Test()` → object created in heap, `x = 5`
5. `obj` reference stored in stack
6. `obj.x` (5) + `y` (10) = 15 → stored in `z` (stack)
7. Method ends → stack frame destroyed
8. JVM exits → GC cleans heap

---

Would you like me to deep-dive into **JIT compilation internals**, **garbage collection algorithms**, or **custom classloader implementation**?

